certbot_dns_stackpath/__init__.py
certbot_dns_stackpath/_internal/__init__.py
certbot_dns_stackpath/_internal/dns_stackpath.py
certbot_dns_stackpath-0.9.0.dev0.dist-info/LICENSE.txt
certbot_dns_stackpath-0.9.0.dev0.dist-info/METADATA
certbot_dns_stackpath-0.9.0.dev0.dist-info/WHEEL
certbot_dns_stackpath-0.9.0.dev0.dist-info/entry_points.txt
certbot_dns_stackpath-0.9.0.dev0.dist-info/top_level.txt
certbot_dns_stackpath-0.9.0.dev0.dist-info/RECORD
