Metadata-Version: 2.1
Name: certbot-dns-stackpath
Version: 0.9.0.dev0
Summary: StackPath DNS Authenticator plugin for Certbot
Home-page: https://github.com/fxa90id/certbot-dns-stackpath
Author: fxa90id
Author-email: fxa90id@pm.me
License: Apache License 2.0
Platform: UNKNOWN
Classifier: Development Status :: 4 - Beta
Classifier: Environment :: Plugins
Classifier: Intended Audience :: System Administrators
Classifier: License :: OSI Approved :: Apache Software License
Classifier: Operating System :: POSIX :: Linux
Classifier: Programming Language :: Python
Classifier: Programming Language :: Python :: 3
Classifier: Programming Language :: Python :: 3.6
Classifier: Programming Language :: Python :: 3.7
Classifier: Programming Language :: Python :: 3.8
Classifier: Programming Language :: Python :: 3.9
Classifier: Topic :: Internet :: WWW/HTTP
Classifier: Topic :: Security
Classifier: Topic :: System :: Installation/Setup
Classifier: Topic :: System :: Networking
Classifier: Topic :: System :: Systems Administration
Classifier: Topic :: Utilities
Requires-Python: >=3.6
Requires-Dist: pystackpath (<1.0.0,>=0.5.0)
Requires-Dist: setuptools (>=39.0.1)
Requires-Dist: zope.interface
Requires-Dist: requests
Requires-Dist: acme (>=0.31.0)
Requires-Dist: certbot (>=1.1.0)
Provides-Extra: docs
Requires-Dist: Sphinx (>=1.0) ; extra == 'docs'
Requires-Dist: sphinx-rtd-theme ; extra == 'docs'
